localeet/__init__.py
localeet/__main__.py
localeet/get_leetcode_problem.py
localeet/get_version.py
localeet/language_maps.py
localeet-0.2.12.dist-info/METADATA
localeet-0.2.12.dist-info/WHEEL
localeet-0.2.12.dist-info/entry_points.txt
localeet-0.2.12.dist-info/licenses/LICENSE
localeet-0.2.12.dist-info/RECORD
