Metadata-Version: 2.1
Name: localeet
Version: 0.2.12
Summary: A CLI tool to do LeetCode and LeetCode-like exercises locally
Project-URL: homepage, https://pypi.org/project/localeet/
Project-URL: documentation, https://github.com/dannybrown37/localeet#localeet
Project-URL: repository, https://github.com/dannybrown37/localeet
Author-email: Danny Brown <dannybrown37@gmail.com>
License-File: LICENSE
Requires-Dist: bs4
Requires-Dist: click
Requires-Dist: lxml
Requires-Dist: requests
Provides-Extra: dev
Requires-Dist: pre-commit; extra == 'dev'
Requires-Dist: ruff==0.0.263; extra == 'dev'
Provides-Extra: pypi
Requires-Dist: hatchling; extra == 'pypi'
Requires-Dist: twine; extra == 'pypi'
Provides-Extra: test
Requires-Dist: pytest; extra == 'test'
Requires-Dist: pytest-icdiff; extra == 'test'
